{
  "arch_hash": "ced9dfcb174c6a53",
  "run_id": "467e1dae-1b2f-4c18-a6a8-7fa3a3b06586",
  "status": "FAILED",
  "started_at": "2026-01-15T15:36:48.495800",
  "completed_at": "2026-01-15T15:41:52.991186",
  "duration_seconds": 304.495389,
  "terraform_apply": {
    "success": false,
    "resources_created": 0,
    "outputs": {},
    "logs": "Terraform timed out"
  },
  "pytest_results": null,
  "container_logs": "n during call chain: Unable to find operation for request to service s3: PUT /\n2026-01-15T15:36:55.314  INFO --- [et.reactor-1] localstack.request.http    : PUT / => 500\n2026-01-15T15:36:55.378 ERROR --- [et.reactor-1] l.aws.handlers.logging     : exception during call chain: Unable to find operation for request to service s3: PUT /\n2026-01-15T15:36:55.383  INFO --- [et.reactor-1] localstack.request.http    : PUT / => 500\n2026-01-15T15:36:55.463  INFO --- [et.reactor-0] localstack.request.aws     : AWS iam.CreateRole => 200\n2026-01-15T15:36:55.468  INFO --- [et.reactor-0] localstack.request.aws     : AWS iam.PutRolePolicy => 200\n2026-01-15T15:36:55.469 ERROR --- [et.reactor-1] l.aws.handlers.logging     : exception during call chain: Unable to find operation for request to service s3: PUT /\n2026-01-15T15:36:55.470  INFO --- [et.reactor-1] localstack.request.http    : PUT / => 500\n2026-01-15T15:36:55.473  INFO --- [et.reactor-0] localstack.request.aws     : AWS iam.GetRole => 200\n2026-01-15T15:36:55.672 ERROR --- [et.reactor-1] l.aws.handlers.logging     : exception during call chain: Unable to find operation for request to service s3: PUT /\n2026-01-15T15:36:55.673  INFO --- [et.reactor-1] localstack.request.http    : PUT / => 500\n2026-01-15T15:36:55.880  INFO --- [et.reactor-0] localstack.request.aws     : AWS iam.ListRolePolicies => 200\n2026-01-15T15:36:55.883  INFO --- [et.reactor-1] localstack.request.aws     : AWS iam.GetRolePolicy => 200\n2026-01-15T15:36:55.886  INFO --- [et.reactor-0] localstack.request.aws     : AWS iam.ListAttachedRolePolicies => 200\n2026-01-15T15:36:56.144 ERROR --- [et.reactor-2] l.aws.handlers.logging     : exception during call chain: Unable to find operation for request to service s3: PUT /\n2026-01-15T15:36:56.145  INFO --- [et.reactor-2] localstack.request.http    : PUT / => 500\n2026-01-15T15:36:56.458  INFO --- [et.reactor-1] localstack.request.aws     : AWS lambda.CreateFunction => 201\n2026-01-15T15:36:56.942 ERROR --- [et.reactor-2] l.aws.handlers.logging     : exception during call chain: Unable to find operation for request to service s3: PUT /\n2026-01-15T15:36:56.943  INFO --- [et.reactor-2] localstack.request.http    : PUT / => 500\n2026-01-15T15:36:58.593 ERROR --- [et.reactor-0] l.aws.handlers.logging     : exception during call chain: Unable to find operation for request to service s3: PUT /\n2026-01-15T15:36:58.594  INFO --- [et.reactor-0] localstack.request.http    : PUT / => 500\n2026-01-15T15:37:01.588  INFO --- [et.reactor-1] localstack.request.aws     : AWS lambda.GetFunction => 200\n2026-01-15T15:37:01.702 ERROR --- [et.reactor-2] l.aws.handlers.logging     : exception during call chain: Unable to find operation for request to service s3: PUT /\n2026-01-15T15:37:01.702  INFO --- [et.reactor-2] localstack.request.http    : PUT / => 500\n2026-01-15T15:37:01.808  INFO --- [et.reactor-0] localstack.request.aws     : AWS lambda.GetFunction => 200\n2026-01-15T15:37:02.251  INFO --- [et.reactor-1] localstack.request.aws     : AWS lambda.GetFunction => 200\n2026-01-15T15:37:03.065  INFO --- [et.reactor-2] localstack.request.aws     : AWS lambda.GetFunction => 200\n2026-01-15T15:37:04.687  INFO --- [et.reactor-1] localstack.request.aws     : AWS lambda.GetFunction => 200\n2026-01-15T15:37:07.902  INFO --- [et.reactor-2] localstack.request.aws     : AWS lambda.GetFunction => 200\n2026-01-15T15:37:07.913  INFO --- [et.reactor-0] localstack.request.aws     : AWS lambda.GetFunction => 200\n2026-01-15T15:37:07.918  INFO --- [et.reactor-1] localstack.request.aws     : AWS lambda.ListVersionsByFunction => 200\n2026-01-15T15:37:07.921  INFO --- [et.reactor-2] localstack.request.aws     : AWS lambda.GetFunctionCodeSigningConfig => 200\n2026-01-15T15:37:08.925 ERROR --- [et.reactor-0] l.aws.handlers.logging     : exception during call chain: Unable to find operation for request to service s3: PUT /\n2026-01-15T15:37:08.926  INFO --- [et.reactor-0] localstack.request.http    : PUT / => 500\n2026-01-15T15:37:20.792 ERROR --- [et.reactor-2] l.aws.handlers.logging     : exception during call chain: Unable to find operation for request to service s3: PUT /\n2026-01-15T15:37:20.792  INFO --- [et.reactor-2] localstack.request.http    : PUT / => 500\n2026-01-15T15:37:50.754 ERROR --- [et.reactor-0] l.aws.handlers.logging     : exception during call chain: Unable to find operation for request to service s3: PUT /\n2026-01-15T15:37:50.755  INFO --- [et.reactor-0] localstack.request.http    : PUT / => 500\n2026-01-15T15:38:33.438 ERROR --- [et.reactor-2] l.aws.handlers.logging     : exception during call chain: Unable to find operation for request to service s3: PUT /\n2026-01-15T15:38:33.439  INFO --- [et.reactor-2] localstack.request.http    : PUT / => 500\n2026-01-15T15:39:38.302 ERROR --- [et.reactor-0] l.aws.handlers.logging     : exception during call chain: Unable to find operation for request to service s3: PUT /\n2026-01-15T15:39:38.303  INFO --- [et.reactor-0] localstack.request.http    : PUT / => 500\n",
  "error_message": null,
  "preprocessing_delta": {
    "removed_resources": [],
    "stub_info": {
      "files": [
        "src/index.js"
      ],
      "lambdas": [
        "lambda_s3_handler"
      ],
      "stub_types": {
        "src/index.js": "js"
      },
      "directories": [],
      "has_stubs": true,
      "stub_count": 1
    },
    "service_reconciliation": {
      "original_services": [
        "iam",
        "lambda",
        "s3"
      ],
      "final_services": [
        "iam",
        "lambda",
        "s3"
      ],
      "removed_services": [],
      "added_services": [],
      "warnings": [],
      "significant_change": false,
      "change_ratio": 0.0
    },
    "modified_files": [
      "main.tf"
    ],
    "generated_tfvars": {},
    "removed_backends": [],
    "removed_profiles": [],
    "provider_version_changes": [],
    "summary": {
      "resources_removed": 0,
      "stubs_created": 1,
      "files_modified": 1,
      "tfvars_generated": 0,
      "backends_removed": 0,
      "services_removed": 0,
      "has_significant_service_changes": false
    }
  },
  "resource_inventory": null,
  "test_quality": null
}